{
  "index": {
    "links": {
      "/": [
        {
          "source": "/",
          "target": "/cs61b/",
          "text": "CS 61B: Data Structures and Algorithms"
        },
        {
          "source": "/",
          "target": "/cs70/",
          "text": "CS 70: Discrete Math"
        },
        {
          "source": "/",
          "target": "/cs186/",
          "text": "CS 186: Intro to Databases"
        },
        {
          "source": "/",
          "target": "/cs162/",
          "text": "CS 162: Operating Systems"
        },
        {
          "source": "/",
          "target": "/cs168/",
          "text": "CS 168: Intro to the Internet"
        },
        {
          "source": "/",
          "target": "/cs61a/",
          "text": "CS 61A: Structure and Interpretation of Computer Programs"
        },
        {
          "source": "/",
          "target": "/data102/",
          "text": "Data 102: Data, Inference, Decisions"
        },
        {
          "source": "/",
          "target": "/contributing",
          "text": "contributing"
        },
        {
          "source": "/",
          "target": "/contributing",
          "text": "contribution guide"
        }
      ],
      "/cs162/": [
        {
          "source": "/cs162/",
          "target": "/Chapter-1-OS-Basics",
          "text": "OS Basics"
        },
        {
          "source": "/cs162/",
          "target": "/Chapter-2-Processes",
          "text": "Processes"
        },
        {
          "source": "/cs162/",
          "target": "/Chapter-3-Threads",
          "text": "Threads"
        },
        {
          "source": "/cs162/",
          "target": "/Chapter-4-I-O",
          "text": "IO"
        },
        {
          "source": "/cs162/",
          "target": "/Chapter-5-Synchronization",
          "text": "Synchronization"
        },
        {
          "source": "/cs162/",
          "target": "/Chapter-6-Scheduling",
          "text": "Scheduling"
        },
        {
          "source": "/cs162/",
          "target": "/Chapter-7-Address-Translation",
          "text": "Address Translation"
        },
        {
          "source": "/cs162/",
          "target": "/Chapter-8-Caching",
          "text": "Caching"
        },
        {
          "source": "/cs162/",
          "target": "/Chapter-9-File-Systems",
          "text": "File Systems"
        },
        {
          "source": "/cs162/",
          "target": "/Appendix-A-GDB-foobars",
          "text": "GDB Reference"
        },
        {
          "source": "/cs162/",
          "target": "/contributing",
          "text": "contributing guide"
        },
        {
          "source": "/cs162/",
          "target": "/cs162/Chapter-8-Caching",
          "text": "Caching"
        },
        {
          "source": "/cs162/",
          "target": "/cs162/Chapter-5-Synchronization",
          "text": "Synchronization"
        }
      ],
      "/cs168/": [
        {
          "source": "/cs168/",
          "target": "/Intro-to-the-Internet",
          "text": "Intro to the Internet"
        },
        {
          "source": "/cs168/",
          "target": "/CLI",
          "text": "CLI Tools"
        },
        {
          "source": "/cs168/",
          "target": "/Intradomain-Routing",
          "text": "Intradomain Routing"
        },
        {
          "source": "/cs168/",
          "target": "/Measuring-Link-Performance",
          "text": "Measuring Link Performance"
        },
        {
          "source": "/cs168/",
          "target": "/Resource-Sharing-Packet-and-Circuit-Switching",
          "text": "Resource Sharing (Packet and Circuit Switching)"
        },
        {
          "source": "/cs168/",
          "target": "/Internet-Organization-and-Layers",
          "text": "Internet Organization and Layers"
        },
        {
          "source": "/cs168/",
          "target": "/Sockets-and-Ports",
          "text": "Sockets and Ports"
        },
        {
          "source": "/cs168/",
          "target": "/Addressing-IP",
          "text": "Addressing (IP)"
        },
        {
          "source": "/cs168/",
          "target": "/Interdomain-Routing-BGP",
          "text": "Interdomain Routing (BGP)"
        },
        {
          "source": "/cs168/",
          "target": "/TCP",
          "text": "TCP"
        },
        {
          "source": "/cs168/",
          "target": "/Reliability",
          "text": "Reliability"
        },
        {
          "source": "/cs168/",
          "target": "/Congestion-Control",
          "text": "Congestion Control"
        },
        {
          "source": "/cs168/",
          "target": "/DNS",
          "text": "DNS"
        },
        {
          "source": "/cs168/",
          "target": "/Web",
          "text": "Web"
        },
        {
          "source": "/cs168/",
          "target": "/Ethernet",
          "text": "Ethernet"
        },
        {
          "source": "/cs168/",
          "target": "/End-to-End-Operation",
          "text": "End to End Operation"
        },
        {
          "source": "/cs168/",
          "target": "/Final-Review",
          "text": "Final Review"
        },
        {
          "source": "/cs168/",
          "target": "/contributing",
          "text": "contributing guide"
        }
      ],
      "/cs168/TCP": [
        {
          "source": "/cs168/TCP",
          "target": "/reliability",
          "text": "reliability"
        },
        {
          "source": "/cs168/TCP",
          "target": "/congestion-control",
          "text": "congestion control"
        }
      ],
      "/cs168/congestion-control": [
        {
          "source": "/cs168/congestion-control",
          "target": "/resource-sharing-packet-and-circuit-switching",
          "text": "resource sharing (packet and circuit switching)"
        }
      ],
      "/cs168/ethernet": [
        {
          "source": "/cs168/ethernet",
          "target": "/",
          "text": "#Pure ALOHA random access"
        }
      ],
      "/cs168/final-review": [
        {
          "source": "/cs168/final-review",
          "target": "/",
          "text": "#SDN"
        }
      ],
      "/cs168/interdomain-routing-bgp": [
        {
          "source": "/cs168/interdomain-routing-bgp",
          "target": "/intradomain-routing",
          "text": "intradomain routing"
        },
        {
          "source": "/cs168/interdomain-routing-bgp",
          "target": "/addressing-ip",
          "text": "addressing (ip)"
        },
        {
          "source": "/cs168/interdomain-routing-bgp",
          "target": "/intradomain-routing",
          "text": "intradomain routing"
        }
      ],
      "/cs186/": [
        {
          "source": "/cs186/",
          "target": "/cs186/00-SQL-Basics",
          "text": "SQL syntax"
        },
        {
          "source": "/cs186/",
          "target": "/cs186/04-Sorting-and-Hashing",
          "text": "How to improve popular sorting and hashing algorithms to work well with limited memory"
        },
        {
          "source": "/cs186/",
          "target": "/cs186/02-B+-Trees",
          "text": "B+ trees"
        },
        {
          "source": "/cs186/",
          "target": "/cs186/05-Iterators-and-Joins",
          "text": "Join algorithms"
        },
        {
          "source": "/cs186/",
          "target": "/cs186/07-Query-Optimization",
          "text": "Query optimization"
        },
        {
          "source": "/cs186/",
          "target": "/cs186/09-Parallel-Query-Processing",
          "text": "Parallel query processing"
        },
        {
          "source": "/cs186/",
          "target": "/cs186/10-Recovery",
          "text": "Crash Recovery (AERIES)"
        },
        {
          "source": "/cs186/",
          "target": "/cs186/08-Transactions",
          "text": "Database transactions and Concurrency"
        },
        {
          "source": "/cs186/",
          "target": "/cs186/12-ER-Diagrams",
          "text": "Entity-Relationship Diagrams"
        },
        {
          "source": "/cs186/",
          "target": "/io",
          "text": "What is an I/O and why should I care?"
        },
        {
          "source": "/cs186/",
          "target": "/cs61b",
          "text": "CS61B"
        },
        {
          "source": "/cs186/",
          "target": "/cs61b",
          "text": "CS61B notes"
        },
        {
          "source": "/cs186/",
          "target": "/cs186/01-Disks-Buffers-Files",
          "text": "Disks, Buffers, Files"
        },
        {
          "source": "/cs186/",
          "target": "/contributing",
          "text": "contributing guide"
        }
      ],
      "/cs186/00-SQL-Basics": [
        {
          "source": "/cs186/00-SQL-Basics",
          "target": "/",
          "text": "table creation"
        },
        {
          "source": "/cs186/00-SQL-Basics",
          "target": "/01-Disks-Buffers-Files",
          "text": "next section"
        }
      ],
      "/cs186/01-Disks-Buffers-Files": [
        {
          "source": "/cs186/01-Disks-Buffers-Files",
          "target": "/cs186/00%20SQL%20Basics",
          "text": "SQL"
        },
        {
          "source": "/cs186/01-Disks-Buffers-Files",
          "target": "/cs186/io",
          "text": "What is an I/O and why should I care?"
        },
        {
          "source": "/cs186/01-Disks-Buffers-Files",
          "target": "/cs186/11-Distributed-Transactions",
          "text": "Distributed Transactions"
        },
        {
          "source": "/cs186/01-Disks-Buffers-Files",
          "target": "/",
          "text": "Practice Problems section"
        },
        {
          "source": "/cs186/01-Disks-Buffers-Files",
          "target": "/cs186/02-B+-Trees",
          "text": "B+ Trees"
        }
      ],
      "/cs186/07-Query-Optimization": [
        {
          "source": "/cs186/07-Query-Optimization",
          "target": "/",
          "text": "practice"
        }
      ],
      "/cs186/io": [
        {
          "source": "/cs186/io",
          "target": "/cs186/07-Query-Optimization",
          "text": "query optimization"
        }
      ],
      "/cs61a/": [
        {
          "source": "/cs61a/",
          "target": "/cs61a/resources",
          "text": "here"
        },
        {
          "source": "/cs61a/",
          "target": "/cs61a/midterm-tips",
          "text": "here"
        }
      ],
      "/cs61b/": [
        {
          "source": "/cs61b/",
          "target": "/cs61b/oop/dynamic-method-selection",
          "text": "Dynamic Method Selection"
        },
        {
          "source": "/cs61b/",
          "target": "/cs61b/asymptotics/asymptotics-practice",
          "text": "Asymptotics Practice"
        },
        {
          "source": "/cs61b/",
          "target": "/contributing",
          "text": "contributing guide"
        },
        {
          "source": "/cs61b/",
          "target": "/cs61b/abstract-data-types/union-find-disjoint-sets",
          "text": "Union Find (Disjoint Sets)"
        },
        {
          "source": "/cs61b/",
          "target": "/cs61b/abstract-data-types/collections/stacks-and-queues",
          "text": "Stacks and Queues"
        },
        {
          "source": "/cs61b/",
          "target": "/cs61b/abstract-data-types/collections/linked-lists",
          "text": "Linked Lists"
        },
        {
          "source": "/cs61b/",
          "target": "/cs61b/abstract-data-types/collections/sets",
          "text": "Sets"
        },
        {
          "source": "/cs61b/",
          "target": "/algorithms/sorting",
          "text": "Sorting"
        },
        {
          "source": "/cs61b/",
          "target": "/cs61b/algorithms/searching",
          "text": "Searching"
        },
        {
          "source": "/cs61b/",
          "target": "/cs61b/algorithms/searching/binary-search",
          "text": "Binary Search"
        },
        {
          "source": "/cs61b/",
          "target": "/cs61b/algorithms/shortest-paths/",
          "text": "Shortest Paths"
        },
        {
          "source": "/cs61b/",
          "target": "/cs61b/misc-topics/exceptions",
          "text": "Exceptions"
        }
      ],
      "/cs61b/abstract-data-types/binary-trees/": [
        {
          "source": "/cs61b/abstract-data-types/binary-trees/",
          "target": "/../../algorithms/searching/binary-search",
          "text": "Binary Search"
        },
        {
          "source": "/cs61b/abstract-data-types/binary-trees/",
          "target": "/balanced-search-structures",
          "text": "Balanced BSTs"
        },
        {
          "source": "/cs61b/abstract-data-types/binary-trees/",
          "target": "/../graphs",
          "text": "Graphs"
        },
        {
          "source": "/cs61b/abstract-data-types/binary-trees/",
          "target": "/tries",
          "text": "Tries"
        },
        {
          "source": "/cs61b/abstract-data-types/binary-trees/",
          "target": "/../hashing",
          "text": "Hash Tables"
        },
        {
          "source": "/cs61b/abstract-data-types/binary-trees/",
          "target": "/../../algorithms/searching/depth-first-search-dfs",
          "text": "Depth First Search"
        },
        {
          "source": "/cs61b/abstract-data-types/binary-trees/",
          "target": "/../../algorithms/searching/breadth-first-search-bfs",
          "text": "Breadth First Search"
        }
      ],
      "/cs61b/abstract-data-types/binary-trees/balanced-search-structures": [
        {
          "source": "/cs61b/abstract-data-types/binary-trees/balanced-search-structures",
          "target": "/cs61b/binary-trees",
          "text": "Binary Trees"
        }
      ],
      "/cs61b/abstract-data-types/binary-trees/tries": [
        {
          "source": "/cs61b/abstract-data-types/binary-trees/tries",
          "target": "/cs61b/abstract-data-types/hashing",
          "text": "Hashing and Hash Tables"
        },
        {
          "source": "/cs61b/abstract-data-types/binary-trees/tries",
          "target": "/cs61b/abstract-data-types/collections/sets",
          "text": "Sets"
        }
      ],
      "/cs61b/abstract-data-types/collections/": [
        {
          "source": "/cs61b/abstract-data-types/collections/",
          "target": "/linked-lists",
          "text": "Linked Lists"
        },
        {
          "source": "/cs61b/abstract-data-types/collections/",
          "target": "/cs61b/abstract-data-types/collections/sets",
          "text": "Sets"
        },
        {
          "source": "/cs61b/abstract-data-types/collections/",
          "target": "/cs61b/abstract-data-types/hashing",
          "text": "Hashing and Hash Tables"
        },
        {
          "source": "/cs61b/abstract-data-types/collections/",
          "target": "/cs61b/abstract-data-types/collections/stacks-and-queues",
          "text": "Stacks and Queues"
        }
      ],
      "/cs61b/abstract-data-types/collections/arrays": [
        {
          "source": "/cs61b/abstract-data-types/collections/arrays",
          "target": "/cs61b/oop/objects",
          "text": "Java Objects"
        },
        {
          "source": "/cs61b/abstract-data-types/collections/arrays",
          "target": "/cs61b/oop/generics",
          "text": "Generic Types"
        },
        {
          "source": "/cs61b/abstract-data-types/collections/arrays",
          "target": "/cs61b/collections",
          "text": "Collections"
        }
      ],
      "/cs61b/abstract-data-types/collections/linked-lists": [
        {
          "source": "/cs61b/abstract-data-types/collections/linked-lists",
          "target": "/arrays",
          "text": "Arrays"
        }
      ],
      "/cs61b/abstract-data-types/collections/sets": [
        {
          "source": "/cs61b/abstract-data-types/collections/sets",
          "target": "/contributing",
          "text": "help make it better!"
        },
        {
          "source": "/cs61b/abstract-data-types/collections/sets",
          "target": "/../../asymptotics/amortization",
          "text": "resized"
        }
      ],
      "/cs61b/abstract-data-types/collections/stacks-and-queues": [
        {
          "source": "/cs61b/abstract-data-types/collections/stacks-and-queues",
          "target": "/cs61b/algorithms/shortest-paths/dijkstras-algorithm",
          "text": "finding shortest paths using Dijkstra's Algorithm"
        }
      ],
      "/cs61b/abstract-data-types/graphs": [
        {
          "source": "/cs61b/abstract-data-types/graphs",
          "target": "/cs61b/algorithms/searching/depth-first-search-dfs",
          "text": "Depth First Search (DFS)"
        },
        {
          "source": "/cs61b/abstract-data-types/graphs",
          "target": "/cs61b/algorithms/searching/breadth-first-search-bfs",
          "text": "Breadth First Search (BFS)"
        },
        {
          "source": "/cs61b/abstract-data-types/graphs",
          "target": "/cs61b/algorithms/minimum-spanning-trees/",
          "text": "Minimum Spanning Trees"
        },
        {
          "source": "/cs61b/abstract-data-types/graphs",
          "target": "/cs61b/algorithms/shortest-paths/",
          "text": "Shortest Paths"
        },
        {
          "source": "/cs61b/abstract-data-types/graphs",
          "target": "/cs61b/algorithms/shortest-paths/dijkstras-algorithm",
          "text": "Dijkstra's Algorithm"
        },
        {
          "source": "/cs61b/abstract-data-types/graphs",
          "target": "/cs61b/algorithms/shortest-paths/a-search",
          "text": "A* Search"
        },
        {
          "source": "/cs61b/abstract-data-types/graphs",
          "target": "/cs61b/algorithms/minimum-spanning-trees/prims-algorithm",
          "text": "Prim's Algorithm"
        },
        {
          "source": "/cs61b/abstract-data-types/graphs",
          "target": "/cs61b/algorithms/minimum-spanning-trees/kruskals-algorithm",
          "text": "Kruskal's Algorithm"
        }
      ],
      "/cs61b/abstract-data-types/hashing": [
        {
          "source": "/cs61b/abstract-data-types/hashing",
          "target": "/cs61b/asymptotics/amortization",
          "text": "Amortization"
        }
      ],
      "/cs61b/abstract-data-types/union-find-disjoint-sets": [
        {
          "source": "/cs61b/abstract-data-types/union-find-disjoint-sets",
          "target": "/cs61b/algorithms/minimum-spanning-trees/kruskals-algorithm",
          "text": "Kruskal's Algorithm"
        }
      ],
      "/cs61b/algorithms/minimum-spanning-trees/kruskals-algorithm": [
        {
          "source": "/cs61b/algorithms/minimum-spanning-trees/kruskals-algorithm",
          "target": "/./",
          "text": "Minimum Spanning Trees"
        },
        {
          "source": "/cs61b/algorithms/minimum-spanning-trees/kruskals-algorithm",
          "target": "/../../abstract-data-types/union-find-disjoint-sets",
          "text": "Union Find (Disjoint Sets)"
        },
        {
          "source": "/cs61b/algorithms/minimum-spanning-trees/kruskals-algorithm",
          "target": "/../../abstract-data-types/union-find-disjoint-sets",
          "text": "Union Find (Disjoint Sets)"
        },
        {
          "source": "/cs61b/algorithms/minimum-spanning-trees/kruskals-algorithm",
          "target": "/../../abstract-data-types/collections/stacks-and-queues",
          "text": "PriorityQueue"
        }
      ],
      "/cs61b/algorithms/minimum-spanning-trees/prims-algorithm": [
        {
          "source": "/cs61b/algorithms/minimum-spanning-trees/prims-algorithm",
          "target": "/./",
          "text": "Minimum Spanning Trees"
        },
        {
          "source": "/cs61b/algorithms/minimum-spanning-trees/prims-algorithm",
          "target": "/../../abstract-data-types/collections/stacks-and-queues",
          "text": "PriorityQueue"
        },
        {
          "source": "/cs61b/algorithms/minimum-spanning-trees/prims-algorithm",
          "target": "/../shortest-paths/dijkstras-algorithm",
          "text": "Dijkstra's"
        }
      ],
      "/cs61b/algorithms/searching/binary-search": [
        {
          "source": "/cs61b/algorithms/searching/binary-search",
          "target": "/../../abstract-data-types/binary-trees/",
          "text": "binary trees"
        }
      ],
      "/cs61b/algorithms/searching/breadth-first-search-bfs": [
        {
          "source": "/cs61b/algorithms/searching/breadth-first-search-bfs",
          "target": "/depth-first-search-dfs",
          "text": "Depth First Search (DFS)"
        },
        {
          "source": "/cs61b/algorithms/searching/breadth-first-search-bfs",
          "target": "/../shortest-paths/dijkstras-algorithm",
          "text": "Dijkstra's Algorithm"
        }
      ],
      "/cs61b/algorithms/shortest-paths/a-search": [
        {
          "source": "/cs61b/algorithms/shortest-paths/a-search",
          "target": "/dijkstras-algorithm",
          "text": "Dijkstra's Algorithm"
        }
      ],
      "/cs61b/algorithms/shortest-paths/dijkstras-algorithm": [
        {
          "source": "/cs61b/algorithms/shortest-paths/dijkstras-algorithm",
          "target": "/../../abstract-data-types/graphs",
          "text": "Graphs"
        },
        {
          "source": "/cs61b/algorithms/shortest-paths/dijkstras-algorithm",
          "target": "/../../abstract-data-types/collections/stacks-and-queues",
          "text": "Stacks and Queues"
        },
        {
          "source": "/cs61b/algorithms/shortest-paths/dijkstras-algorithm",
          "target": "/./",
          "text": "Shortest Paths"
        }
      ],
      "/cs61b/asymptotics/amortization": [
        {
          "source": "/cs61b/asymptotics/amortization",
          "target": "/asymptotics",
          "text": "Asymptotic Analysis Basics"
        }
      ],
      "/cs61b/asymptotics/asymptotics": [
        {
          "source": "/cs61b/asymptotics/asymptotics",
          "target": "/asymptotics-practice",
          "text": "try some problems!"
        },
        {
          "source": "/cs61b/asymptotics/asymptotics",
          "target": "/asymptotics",
          "text": "Simplify"
        }
      ],
      "/cs61b/asymptotics/asymptotics-practice": [
        {
          "source": "/cs61b/asymptotics/asymptotics-practice",
          "target": "/asymptotics",
          "text": "Asymptotic Analysis Basics"
        }
      ],
      "/cs61b/misc-topics/modular-arithmetic": [
        {
          "source": "/cs61b/misc-topics/modular-arithmetic",
          "target": "/cs61b/oop/objects",
          "text": "Java Objects"
        }
      ],
      "/cs61b/oop/dynamic-method-selection": [
        {
          "source": "/cs61b/oop/dynamic-method-selection",
          "target": "/inheritance",
          "text": "inheritance"
        },
        {
          "source": "/cs61b/oop/dynamic-method-selection",
          "target": "/access-control",
          "text": "access control"
        },
        {
          "source": "/cs61b/oop/dynamic-method-selection",
          "target": "/inheritance",
          "text": "Interfaces"
        },
        {
          "source": "/cs61b/oop/dynamic-method-selection",
          "target": "/../abstract-data-types/collections/",
          "text": "Collections"
        }
      ],
      "/cs61b/oop/generics": [
        {
          "source": "/cs61b/oop/generics",
          "target": "/dynamic-method-selection",
          "text": "Dynamic Method Selection"
        },
        {
          "source": "/cs61b/oop/generics",
          "target": "/inheritance",
          "text": "inheritance rules"
        }
      ],
      "/cs61b/oop/inheritance": [
        {
          "source": "/cs61b/oop/inheritance",
          "target": "/access-control",
          "text": "Access Control"
        },
        {
          "source": "/cs61b/oop/inheritance",
          "target": "/objects",
          "text": "References, Objects, and Types in Java"
        },
        {
          "source": "/cs61b/oop/inheritance",
          "target": "/generics",
          "text": "Generic Types"
        },
        {
          "source": "/cs61b/oop/inheritance",
          "target": "/dynamic-method-selection",
          "text": "Dynamic Method Selection"
        }
      ],
      "/cs61b/oop/objects": [
        {
          "source": "/cs61b/oop/objects",
          "target": "/cs61b/misc-topics/modular-arithmetic",
          "text": "Modular Arithmetic and Bit Manipulation"
        },
        {
          "source": "/cs61b/oop/objects",
          "target": "/../abstract-data-types/collections/",
          "text": "collections"
        }
      ],
      "/cs70/": [
        {
          "source": "/cs70/",
          "target": "/contributing",
          "text": "contributing guide"
        },
        {
          "source": "/cs70/",
          "target": "/cs70/latex-reference",
          "text": "LaTeX Reference"
        }
      ],
      "/cs70/discrete-math/graphs": [
        {
          "source": "/cs70/discrete-math/graphs",
          "target": "/cs61b/abstract-data-types/graphs",
          "text": "61B version"
        }
      ],
      "/cs70/discrete-math/modular-arithmetic": [
        {
          "source": "/cs70/discrete-math/modular-arithmetic",
          "target": "/cs70/discrete-math/rsa-cryptography",
          "text": "cryptography"
        },
        {
          "source": "/cs70/discrete-math/modular-arithmetic",
          "target": "/cs70/discrete-math/polynomials",
          "text": "error correction"
        },
        {
          "source": "/cs70/discrete-math/modular-arithmetic",
          "target": "/cs70/discrete-math/rsa-cryptography",
          "text": "RSA Cryptography"
        }
      ],
      "/cs70/discrete-math/overview": [
        {
          "source": "/cs70/discrete-math/overview",
          "target": "/propositional-logic",
          "text": "Propositional logic"
        },
        {
          "source": "/cs70/discrete-math/overview",
          "target": "/proofs",
          "text": "Proofs"
        },
        {
          "source": "/cs70/discrete-math/overview",
          "target": "/stable-matching",
          "text": "Stable Matching"
        },
        {
          "source": "/cs70/discrete-math/overview",
          "target": "/classes/cs70/discrete-math/graphs",
          "text": "Graph theory"
        },
        {
          "source": "/cs70/discrete-math/overview",
          "target": "/modular-arithmetic",
          "text": "Modular arithmetic"
        },
        {
          "source": "/cs70/discrete-math/overview",
          "target": "/rsa-cryptography",
          "text": "RSA Cryptography"
        },
        {
          "source": "/cs70/discrete-math/overview",
          "target": "/polynomials",
          "text": "Polynomials"
        }
      ],
      "/cs70/discrete-math/rsa-cryptography": [
        {
          "source": "/cs70/discrete-math/rsa-cryptography",
          "target": "/cs70/discrete-math/polynomials",
          "text": "soon"
        }
      ],
      "/cs70/probability/concentration-inequalities": [
        {
          "source": "/cs70/probability/concentration-inequalities",
          "target": "/data102/concentration%20inequalities",
          "text": "Data 102 notes"
        }
      ],
      "/cs70/probability/probability-overview": [
        {
          "source": "/cs70/probability/probability-overview",
          "target": "/cs70/probability/counting",
          "text": "Counting"
        },
        {
          "source": "/cs70/probability/probability-overview",
          "target": "/cs70/probability/discrete-probability",
          "text": "Discrete probability distributions"
        },
        {
          "source": "/cs70/probability/probability-overview",
          "target": "/cs70/probability/continuous-probability",
          "text": "Continuous probability distributions"
        },
        {
          "source": "/cs70/probability/probability-overview",
          "target": "/cs70/probability/markov-chains",
          "text": "Markov chains"
        },
        {
          "source": "/cs70/probability/probability-overview",
          "target": "/cs70/probability/expectation-and-variance",
          "text": "Expectation and variance"
        },
        {
          "source": "/cs70/probability/probability-overview",
          "target": "/cs70/probability/concentration-inequalities",
          "text": "Concentration inequalities"
        }
      ],
      "/data102/": [
        {
          "source": "/data102/",
          "target": "/Binary-Decision-Making",
          "text": "Binary Decision Making"
        },
        {
          "source": "/data102/",
          "target": "/Hypothesis-Testing",
          "text": "Hypothesis Testing"
        },
        {
          "source": "/data102/",
          "target": "/Decision-Theory",
          "text": "Decision Theory"
        },
        {
          "source": "/data102/",
          "target": "/Parameter-Estimation",
          "text": "Parameter Estimation"
        },
        {
          "source": "/data102/",
          "target": "/Sampling",
          "text": "Sampling"
        },
        {
          "source": "/data102/",
          "target": "/Regression-and-GLMs",
          "text": "Regression and GLMs"
        },
        {
          "source": "/data102/",
          "target": "/Nonparametric-Methods",
          "text": "Nonparametric Methods"
        },
        {
          "source": "/data102/",
          "target": "/Interpretability",
          "text": "Interpretability"
        },
        {
          "source": "/data102/",
          "target": "/Causality",
          "text": "Causality"
        },
        {
          "source": "/data102/",
          "target": "/Concentration-Inequalities",
          "text": "Concentration Inequalities"
        },
        {
          "source": "/data102/",
          "target": "/Bandits",
          "text": "Bandits"
        },
        {
          "source": "/data102/",
          "target": "/Markov-Decision-Processes",
          "text": "Markov Decision Processes"
        },
        {
          "source": "/data102/",
          "target": "/Reinforcement-Learning",
          "text": "Reinforcement Learning"
        },
        {
          "source": "/data102/",
          "target": "/contributing",
          "text": "contributing guide"
        }
      ],
      "/data102/causality": [
        {
          "source": "/data102/causality",
          "target": "/04-Bayes-Nets",
          "text": "04 Bayes Nets"
        }
      ],
      "/data102/decision-theory": [
        {
          "source": "/data102/decision-theory",
          "target": "/binary-decision-making",
          "text": "binary decision making"
        },
        {
          "source": "/data102/decision-theory",
          "target": "/hypothesis-testing",
          "text": "hypothesis testing"
        }
      ],
      "/data102/hypothesis-testing": [
        {
          "source": "/data102/hypothesis-testing",
          "target": "/binary-decision-making",
          "text": "binary decision making"
        }
      ],
      "/data102/regression-and-glms": [
        {
          "source": "/data102/regression-and-glms",
          "target": "/",
          "text": "#Model Checking"
        },
        {
          "source": "/data102/regression-and-glms",
          "target": "/",
          "text": "#Credible Intervals"
        }
      ]
    },
    "backlinks": {
      "/": [
        {
          "source": "/cs168/ethernet",
          "target": "/",
          "text": "#Pure ALOHA random access"
        },
        {
          "source": "/cs168/final-review",
          "target": "/",
          "text": "#SDN"
        },
        {
          "source": "/cs186/00-SQL-Basics",
          "target": "/",
          "text": "table creation"
        },
        {
          "source": "/cs186/01-Disks-Buffers-Files",
          "target": "/",
          "text": "Practice Problems section"
        },
        {
          "source": "/cs186/07-Query-Optimization",
          "target": "/",
          "text": "practice"
        },
        {
          "source": "/data102/regression-and-glms",
          "target": "/",
          "text": "#Model Checking"
        },
        {
          "source": "/data102/regression-and-glms",
          "target": "/",
          "text": "#Credible Intervals"
        }
      ],
      "/../../abstract-data-types/binary-trees/": [
        {
          "source": "/cs61b/algorithms/searching/binary-search",
          "target": "/../../abstract-data-types/binary-trees/",
          "text": "binary trees"
        }
      ],
      "/../../abstract-data-types/collections/stacks-and-queues": [
        {
          "source": "/cs61b/algorithms/minimum-spanning-trees/kruskals-algorithm",
          "target": "/../../abstract-data-types/collections/stacks-and-queues",
          "text": "PriorityQueue"
        },
        {
          "source": "/cs61b/algorithms/minimum-spanning-trees/prims-algorithm",
          "target": "/../../abstract-data-types/collections/stacks-and-queues",
          "text": "PriorityQueue"
        },
        {
          "source": "/cs61b/algorithms/shortest-paths/dijkstras-algorithm",
          "target": "/../../abstract-data-types/collections/stacks-and-queues",
          "text": "Stacks and Queues"
        }
      ],
      "/../../abstract-data-types/graphs": [
        {
          "source": "/cs61b/algorithms/shortest-paths/dijkstras-algorithm",
          "target": "/../../abstract-data-types/graphs",
          "text": "Graphs"
        }
      ],
      "/../../abstract-data-types/union-find-disjoint-sets": [
        {
          "source": "/cs61b/algorithms/minimum-spanning-trees/kruskals-algorithm",
          "target": "/../../abstract-data-types/union-find-disjoint-sets",
          "text": "Union Find (Disjoint Sets)"
        },
        {
          "source": "/cs61b/algorithms/minimum-spanning-trees/kruskals-algorithm",
          "target": "/../../abstract-data-types/union-find-disjoint-sets",
          "text": "Union Find (Disjoint Sets)"
        }
      ],
      "/../../algorithms/searching/binary-search": [
        {
          "source": "/cs61b/abstract-data-types/binary-trees/",
          "target": "/../../algorithms/searching/binary-search",
          "text": "Binary Search"
        }
      ],
      "/../../algorithms/searching/breadth-first-search-bfs": [
        {
          "source": "/cs61b/abstract-data-types/binary-trees/",
          "target": "/../../algorithms/searching/breadth-first-search-bfs",
          "text": "Breadth First Search"
        }
      ],
      "/../../algorithms/searching/depth-first-search-dfs": [
        {
          "source": "/cs61b/abstract-data-types/binary-trees/",
          "target": "/../../algorithms/searching/depth-first-search-dfs",
          "text": "Depth First Search"
        }
      ],
      "/../../asymptotics/amortization": [
        {
          "source": "/cs61b/abstract-data-types/collections/sets",
          "target": "/../../asymptotics/amortization",
          "text": "resized"
        }
      ],
      "/../abstract-data-types/collections/": [
        {
          "source": "/cs61b/oop/dynamic-method-selection",
          "target": "/../abstract-data-types/collections/",
          "text": "Collections"
        },
        {
          "source": "/cs61b/oop/objects",
          "target": "/../abstract-data-types/collections/",
          "text": "collections"
        }
      ],
      "/../graphs": [
        {
          "source": "/cs61b/abstract-data-types/binary-trees/",
          "target": "/../graphs",
          "text": "Graphs"
        }
      ],
      "/../hashing": [
        {
          "source": "/cs61b/abstract-data-types/binary-trees/",
          "target": "/../hashing",
          "text": "Hash Tables"
        }
      ],
      "/../shortest-paths/dijkstras-algorithm": [
        {
          "source": "/cs61b/algorithms/minimum-spanning-trees/prims-algorithm",
          "target": "/../shortest-paths/dijkstras-algorithm",
          "text": "Dijkstra's"
        },
        {
          "source": "/cs61b/algorithms/searching/breadth-first-search-bfs",
          "target": "/../shortest-paths/dijkstras-algorithm",
          "text": "Dijkstra's Algorithm"
        }
      ],
      "/./": [
        {
          "source": "/cs61b/algorithms/minimum-spanning-trees/kruskals-algorithm",
          "target": "/./",
          "text": "Minimum Spanning Trees"
        },
        {
          "source": "/cs61b/algorithms/minimum-spanning-trees/prims-algorithm",
          "target": "/./",
          "text": "Minimum Spanning Trees"
        },
        {
          "source": "/cs61b/algorithms/shortest-paths/dijkstras-algorithm",
          "target": "/./",
          "text": "Shortest Paths"
        }
      ],
      "/01-Disks-Buffers-Files": [
        {
          "source": "/cs186/00-SQL-Basics",
          "target": "/01-Disks-Buffers-Files",
          "text": "next section"
        }
      ],
      "/04-Bayes-Nets": [
        {
          "source": "/data102/causality",
          "target": "/04-Bayes-Nets",
          "text": "04 Bayes Nets"
        }
      ],
      "/Addressing-IP": [
        {
          "source": "/cs168/",
          "target": "/Addressing-IP",
          "text": "Addressing (IP)"
        }
      ],
      "/Appendix-A-GDB-foobars": [
        {
          "source": "/cs162/",
          "target": "/Appendix-A-GDB-foobars",
          "text": "GDB Reference"
        }
      ],
      "/Bandits": [
        {
          "source": "/data102/",
          "target": "/Bandits",
          "text": "Bandits"
        }
      ],
      "/Binary-Decision-Making": [
        {
          "source": "/data102/",
          "target": "/Binary-Decision-Making",
          "text": "Binary Decision Making"
        }
      ],
      "/CLI": [
        {
          "source": "/cs168/",
          "target": "/CLI",
          "text": "CLI Tools"
        }
      ],
      "/Causality": [
        {
          "source": "/data102/",
          "target": "/Causality",
          "text": "Causality"
        }
      ],
      "/Chapter-1-OS-Basics": [
        {
          "source": "/cs162/",
          "target": "/Chapter-1-OS-Basics",
          "text": "OS Basics"
        }
      ],
      "/Chapter-2-Processes": [
        {
          "source": "/cs162/",
          "target": "/Chapter-2-Processes",
          "text": "Processes"
        }
      ],
      "/Chapter-3-Threads": [
        {
          "source": "/cs162/",
          "target": "/Chapter-3-Threads",
          "text": "Threads"
        }
      ],
      "/Chapter-4-I-O": [
        {
          "source": "/cs162/",
          "target": "/Chapter-4-I-O",
          "text": "IO"
        }
      ],
      "/Chapter-5-Synchronization": [
        {
          "source": "/cs162/",
          "target": "/Chapter-5-Synchronization",
          "text": "Synchronization"
        }
      ],
      "/Chapter-6-Scheduling": [
        {
          "source": "/cs162/",
          "target": "/Chapter-6-Scheduling",
          "text": "Scheduling"
        }
      ],
      "/Chapter-7-Address-Translation": [
        {
          "source": "/cs162/",
          "target": "/Chapter-7-Address-Translation",
          "text": "Address Translation"
        }
      ],
      "/Chapter-8-Caching": [
        {
          "source": "/cs162/",
          "target": "/Chapter-8-Caching",
          "text": "Caching"
        }
      ],
      "/Chapter-9-File-Systems": [
        {
          "source": "/cs162/",
          "target": "/Chapter-9-File-Systems",
          "text": "File Systems"
        }
      ],
      "/Concentration-Inequalities": [
        {
          "source": "/data102/",
          "target": "/Concentration-Inequalities",
          "text": "Concentration Inequalities"
        }
      ],
      "/Congestion-Control": [
        {
          "source": "/cs168/",
          "target": "/Congestion-Control",
          "text": "Congestion Control"
        }
      ],
      "/DNS": [
        {
          "source": "/cs168/",
          "target": "/DNS",
          "text": "DNS"
        }
      ],
      "/Decision-Theory": [
        {
          "source": "/data102/",
          "target": "/Decision-Theory",
          "text": "Decision Theory"
        }
      ],
      "/End-to-End-Operation": [
        {
          "source": "/cs168/",
          "target": "/End-to-End-Operation",
          "text": "End to End Operation"
        }
      ],
      "/Ethernet": [
        {
          "source": "/cs168/",
          "target": "/Ethernet",
          "text": "Ethernet"
        }
      ],
      "/Final-Review": [
        {
          "source": "/cs168/",
          "target": "/Final-Review",
          "text": "Final Review"
        }
      ],
      "/Hypothesis-Testing": [
        {
          "source": "/data102/",
          "target": "/Hypothesis-Testing",
          "text": "Hypothesis Testing"
        }
      ],
      "/Interdomain-Routing-BGP": [
        {
          "source": "/cs168/",
          "target": "/Interdomain-Routing-BGP",
          "text": "Interdomain Routing (BGP)"
        }
      ],
      "/Internet-Organization-and-Layers": [
        {
          "source": "/cs168/",
          "target": "/Internet-Organization-and-Layers",
          "text": "Internet Organization and Layers"
        }
      ],
      "/Interpretability": [
        {
          "source": "/data102/",
          "target": "/Interpretability",
          "text": "Interpretability"
        }
      ],
      "/Intradomain-Routing": [
        {
          "source": "/cs168/",
          "target": "/Intradomain-Routing",
          "text": "Intradomain Routing"
        }
      ],
      "/Intro-to-the-Internet": [
        {
          "source": "/cs168/",
          "target": "/Intro-to-the-Internet",
          "text": "Intro to the Internet"
        }
      ],
      "/Markov-Decision-Processes": [
        {
          "source": "/data102/",
          "target": "/Markov-Decision-Processes",
          "text": "Markov Decision Processes"
        }
      ],
      "/Measuring-Link-Performance": [
        {
          "source": "/cs168/",
          "target": "/Measuring-Link-Performance",
          "text": "Measuring Link Performance"
        }
      ],
      "/Nonparametric-Methods": [
        {
          "source": "/data102/",
          "target": "/Nonparametric-Methods",
          "text": "Nonparametric Methods"
        }
      ],
      "/Parameter-Estimation": [
        {
          "source": "/data102/",
          "target": "/Parameter-Estimation",
          "text": "Parameter Estimation"
        }
      ],
      "/Regression-and-GLMs": [
        {
          "source": "/data102/",
          "target": "/Regression-and-GLMs",
          "text": "Regression and GLMs"
        }
      ],
      "/Reinforcement-Learning": [
        {
          "source": "/data102/",
          "target": "/Reinforcement-Learning",
          "text": "Reinforcement Learning"
        }
      ],
      "/Reliability": [
        {
          "source": "/cs168/",
          "target": "/Reliability",
          "text": "Reliability"
        }
      ],
      "/Resource-Sharing-Packet-and-Circuit-Switching": [
        {
          "source": "/cs168/",
          "target": "/Resource-Sharing-Packet-and-Circuit-Switching",
          "text": "Resource Sharing (Packet and Circuit Switching)"
        }
      ],
      "/Sampling": [
        {
          "source": "/data102/",
          "target": "/Sampling",
          "text": "Sampling"
        }
      ],
      "/Sockets-and-Ports": [
        {
          "source": "/cs168/",
          "target": "/Sockets-and-Ports",
          "text": "Sockets and Ports"
        }
      ],
      "/TCP": [
        {
          "source": "/cs168/",
          "target": "/TCP",
          "text": "TCP"
        }
      ],
      "/Web": [
        {
          "source": "/cs168/",
          "target": "/Web",
          "text": "Web"
        }
      ],
      "/access-control": [
        {
          "source": "/cs61b/oop/dynamic-method-selection",
          "target": "/access-control",
          "text": "access control"
        },
        {
          "source": "/cs61b/oop/inheritance",
          "target": "/access-control",
          "text": "Access Control"
        }
      ],
      "/addressing-ip": [
        {
          "source": "/cs168/interdomain-routing-bgp",
          "target": "/addressing-ip",
          "text": "addressing (ip)"
        }
      ],
      "/algorithms/sorting": [
        {
          "source": "/cs61b/",
          "target": "/algorithms/sorting",
          "text": "Sorting"
        }
      ],
      "/arrays": [
        {
          "source": "/cs61b/abstract-data-types/collections/linked-lists",
          "target": "/arrays",
          "text": "Arrays"
        }
      ],
      "/asymptotics": [
        {
          "source": "/cs61b/asymptotics/amortization",
          "target": "/asymptotics",
          "text": "Asymptotic Analysis Basics"
        },
        {
          "source": "/cs61b/asymptotics/asymptotics-practice",
          "target": "/asymptotics",
          "text": "Asymptotic Analysis Basics"
        },
        {
          "source": "/cs61b/asymptotics/asymptotics",
          "target": "/asymptotics",
          "text": "Simplify"
        }
      ],
      "/asymptotics-practice": [
        {
          "source": "/cs61b/asymptotics/asymptotics",
          "target": "/asymptotics-practice",
          "text": "try some problems!"
        }
      ],
      "/balanced-search-structures": [
        {
          "source": "/cs61b/abstract-data-types/binary-trees/",
          "target": "/balanced-search-structures",
          "text": "Balanced BSTs"
        }
      ],
      "/binary-decision-making": [
        {
          "source": "/data102/decision-theory",
          "target": "/binary-decision-making",
          "text": "binary decision making"
        },
        {
          "source": "/data102/hypothesis-testing",
          "target": "/binary-decision-making",
          "text": "binary decision making"
        }
      ],
      "/classes/cs70/discrete-math/graphs": [
        {
          "source": "/cs70/discrete-math/overview",
          "target": "/classes/cs70/discrete-math/graphs",
          "text": "Graph theory"
        }
      ],
      "/congestion-control": [
        {
          "source": "/cs168/TCP",
          "target": "/congestion-control",
          "text": "congestion control"
        }
      ],
      "/contributing": [
        {
          "source": "/",
          "target": "/contributing",
          "text": "contributing"
        },
        {
          "source": "/",
          "target": "/contributing",
          "text": "contribution guide"
        },
        {
          "source": "/cs162/",
          "target": "/contributing",
          "text": "contributing guide"
        },
        {
          "source": "/cs168/",
          "target": "/contributing",
          "text": "contributing guide"
        },
        {
          "source": "/cs186/",
          "target": "/contributing",
          "text": "contributing guide"
        },
        {
          "source": "/cs61b/",
          "target": "/contributing",
          "text": "contributing guide"
        },
        {
          "source": "/cs61b/abstract-data-types/collections/sets",
          "target": "/contributing",
          "text": "help make it better!"
        },
        {
          "source": "/cs70/",
          "target": "/contributing",
          "text": "contributing guide"
        },
        {
          "source": "/data102/",
          "target": "/contributing",
          "text": "contributing guide"
        }
      ],
      "/cs162/": [
        {
          "source": "/",
          "target": "/cs162/",
          "text": "CS 162: Operating Systems"
        }
      ],
      "/cs162/Chapter-5-Synchronization": [
        {
          "source": "/cs162/",
          "target": "/cs162/Chapter-5-Synchronization",
          "text": "Synchronization"
        }
      ],
      "/cs162/Chapter-8-Caching": [
        {
          "source": "/cs162/",
          "target": "/cs162/Chapter-8-Caching",
          "text": "Caching"
        }
      ],
      "/cs168/": [
        {
          "source": "/",
          "target": "/cs168/",
          "text": "CS 168: Intro to the Internet"
        }
      ],
      "/cs186/": [
        {
          "source": "/",
          "target": "/cs186/",
          "text": "CS 186: Intro to Databases"
        }
      ],
      "/cs186/00%20SQL%20Basics": [
        {
          "source": "/cs186/01-Disks-Buffers-Files",
          "target": "/cs186/00%20SQL%20Basics",
          "text": "SQL"
        }
      ],
      "/cs186/00-SQL-Basics": [
        {
          "source": "/cs186/",
          "target": "/cs186/00-SQL-Basics",
          "text": "SQL syntax"
        }
      ],
      "/cs186/01-Disks-Buffers-Files": [
        {
          "source": "/cs186/",
          "target": "/cs186/01-Disks-Buffers-Files",
          "text": "Disks, Buffers, Files"
        }
      ],
      "/cs186/02-B+-Trees": [
        {
          "source": "/cs186/01-Disks-Buffers-Files",
          "target": "/cs186/02-B+-Trees",
          "text": "B+ Trees"
        },
        {
          "source": "/cs186/",
          "target": "/cs186/02-B+-Trees",
          "text": "B+ trees"
        }
      ],
      "/cs186/04-Sorting-and-Hashing": [
        {
          "source": "/cs186/",
          "target": "/cs186/04-Sorting-and-Hashing",
          "text": "How to improve popular sorting and hashing algorithms to work well with limited memory"
        }
      ],
      "/cs186/05-Iterators-and-Joins": [
        {
          "source": "/cs186/",
          "target": "/cs186/05-Iterators-and-Joins",
          "text": "Join algorithms"
        }
      ],
      "/cs186/07-Query-Optimization": [
        {
          "source": "/cs186/",
          "target": "/cs186/07-Query-Optimization",
          "text": "Query optimization"
        },
        {
          "source": "/cs186/io",
          "target": "/cs186/07-Query-Optimization",
          "text": "query optimization"
        }
      ],
      "/cs186/08-Transactions": [
        {
          "source": "/cs186/",
          "target": "/cs186/08-Transactions",
          "text": "Database transactions and Concurrency"
        }
      ],
      "/cs186/09-Parallel-Query-Processing": [
        {
          "source": "/cs186/",
          "target": "/cs186/09-Parallel-Query-Processing",
          "text": "Parallel query processing"
        }
      ],
      "/cs186/10-Recovery": [
        {
          "source": "/cs186/",
          "target": "/cs186/10-Recovery",
          "text": "Crash Recovery (AERIES)"
        }
      ],
      "/cs186/11-Distributed-Transactions": [
        {
          "source": "/cs186/01-Disks-Buffers-Files",
          "target": "/cs186/11-Distributed-Transactions",
          "text": "Distributed Transactions"
        }
      ],
      "/cs186/12-ER-Diagrams": [
        {
          "source": "/cs186/",
          "target": "/cs186/12-ER-Diagrams",
          "text": "Entity-Relationship Diagrams"
        }
      ],
      "/cs186/io": [
        {
          "source": "/cs186/01-Disks-Buffers-Files",
          "target": "/cs186/io",
          "text": "What is an I/O and why should I care?"
        }
      ],
      "/cs61a/": [
        {
          "source": "/",
          "target": "/cs61a/",
          "text": "CS 61A: Structure and Interpretation of Computer Programs"
        }
      ],
      "/cs61a/midterm-tips": [
        {
          "source": "/cs61a/",
          "target": "/cs61a/midterm-tips",
          "text": "here"
        }
      ],
      "/cs61a/resources": [
        {
          "source": "/cs61a/",
          "target": "/cs61a/resources",
          "text": "here"
        }
      ],
      "/cs61b": [
        {
          "source": "/cs186/",
          "target": "/cs61b",
          "text": "CS61B"
        },
        {
          "source": "/cs186/",
          "target": "/cs61b",
          "text": "CS61B notes"
        }
      ],
      "/cs61b/": [
        {
          "source": "/",
          "target": "/cs61b/",
          "text": "CS 61B: Data Structures and Algorithms"
        }
      ],
      "/cs61b/abstract-data-types/collections/linked-lists": [
        {
          "source": "/cs61b/",
          "target": "/cs61b/abstract-data-types/collections/linked-lists",
          "text": "Linked Lists"
        }
      ],
      "/cs61b/abstract-data-types/collections/sets": [
        {
          "source": "/cs61b/",
          "target": "/cs61b/abstract-data-types/collections/sets",
          "text": "Sets"
        },
        {
          "source": "/cs61b/abstract-data-types/binary-trees/tries",
          "target": "/cs61b/abstract-data-types/collections/sets",
          "text": "Sets"
        },
        {
          "source": "/cs61b/abstract-data-types/collections/",
          "target": "/cs61b/abstract-data-types/collections/sets",
          "text": "Sets"
        }
      ],
      "/cs61b/abstract-data-types/collections/stacks-and-queues": [
        {
          "source": "/cs61b/",
          "target": "/cs61b/abstract-data-types/collections/stacks-and-queues",
          "text": "Stacks and Queues"
        },
        {
          "source": "/cs61b/abstract-data-types/collections/",
          "target": "/cs61b/abstract-data-types/collections/stacks-and-queues",
          "text": "Stacks and Queues"
        }
      ],
      "/cs61b/abstract-data-types/graphs": [
        {
          "source": "/cs70/discrete-math/graphs",
          "target": "/cs61b/abstract-data-types/graphs",
          "text": "61B version"
        }
      ],
      "/cs61b/abstract-data-types/hashing": [
        {
          "source": "/cs61b/abstract-data-types/binary-trees/tries",
          "target": "/cs61b/abstract-data-types/hashing",
          "text": "Hashing and Hash Tables"
        },
        {
          "source": "/cs61b/abstract-data-types/collections/",
          "target": "/cs61b/abstract-data-types/hashing",
          "text": "Hashing and Hash Tables"
        }
      ],
      "/cs61b/abstract-data-types/union-find-disjoint-sets": [
        {
          "source": "/cs61b/",
          "target": "/cs61b/abstract-data-types/union-find-disjoint-sets",
          "text": "Union Find (Disjoint Sets)"
        }
      ],
      "/cs61b/algorithms/minimum-spanning-trees/": [
        {
          "source": "/cs61b/abstract-data-types/graphs",
          "target": "/cs61b/algorithms/minimum-spanning-trees/",
          "text": "Minimum Spanning Trees"
        }
      ],
      "/cs61b/algorithms/minimum-spanning-trees/kruskals-algorithm": [
        {
          "source": "/cs61b/abstract-data-types/graphs",
          "target": "/cs61b/algorithms/minimum-spanning-trees/kruskals-algorithm",
          "text": "Kruskal's Algorithm"
        },
        {
          "source": "/cs61b/abstract-data-types/union-find-disjoint-sets",
          "target": "/cs61b/algorithms/minimum-spanning-trees/kruskals-algorithm",
          "text": "Kruskal's Algorithm"
        }
      ],
      "/cs61b/algorithms/minimum-spanning-trees/prims-algorithm": [
        {
          "source": "/cs61b/abstract-data-types/graphs",
          "target": "/cs61b/algorithms/minimum-spanning-trees/prims-algorithm",
          "text": "Prim's Algorithm"
        }
      ],
      "/cs61b/algorithms/searching": [
        {
          "source": "/cs61b/",
          "target": "/cs61b/algorithms/searching",
          "text": "Searching"
        }
      ],
      "/cs61b/algorithms/searching/binary-search": [
        {
          "source": "/cs61b/",
          "target": "/cs61b/algorithms/searching/binary-search",
          "text": "Binary Search"
        }
      ],
      "/cs61b/algorithms/searching/breadth-first-search-bfs": [
        {
          "source": "/cs61b/abstract-data-types/graphs",
          "target": "/cs61b/algorithms/searching/breadth-first-search-bfs",
          "text": "Breadth First Search (BFS)"
        }
      ],
      "/cs61b/algorithms/searching/depth-first-search-dfs": [
        {
          "source": "/cs61b/abstract-data-types/graphs",
          "target": "/cs61b/algorithms/searching/depth-first-search-dfs",
          "text": "Depth First Search (DFS)"
        }
      ],
      "/cs61b/algorithms/shortest-paths/": [
        {
          "source": "/cs61b/",
          "target": "/cs61b/algorithms/shortest-paths/",
          "text": "Shortest Paths"
        },
        {
          "source": "/cs61b/abstract-data-types/graphs",
          "target": "/cs61b/algorithms/shortest-paths/",
          "text": "Shortest Paths"
        }
      ],
      "/cs61b/algorithms/shortest-paths/a-search": [
        {
          "source": "/cs61b/abstract-data-types/graphs",
          "target": "/cs61b/algorithms/shortest-paths/a-search",
          "text": "A* Search"
        }
      ],
      "/cs61b/algorithms/shortest-paths/dijkstras-algorithm": [
        {
          "source": "/cs61b/abstract-data-types/collections/stacks-and-queues",
          "target": "/cs61b/algorithms/shortest-paths/dijkstras-algorithm",
          "text": "finding shortest paths using Dijkstra's Algorithm"
        },
        {
          "source": "/cs61b/abstract-data-types/graphs",
          "target": "/cs61b/algorithms/shortest-paths/dijkstras-algorithm",
          "text": "Dijkstra's Algorithm"
        }
      ],
      "/cs61b/asymptotics/amortization": [
        {
          "source": "/cs61b/abstract-data-types/hashing",
          "target": "/cs61b/asymptotics/amortization",
          "text": "Amortization"
        }
      ],
      "/cs61b/asymptotics/asymptotics-practice": [
        {
          "source": "/cs61b/",
          "target": "/cs61b/asymptotics/asymptotics-practice",
          "text": "Asymptotics Practice"
        }
      ],
      "/cs61b/binary-trees": [
        {
          "source": "/cs61b/abstract-data-types/binary-trees/balanced-search-structures",
          "target": "/cs61b/binary-trees",
          "text": "Binary Trees"
        }
      ],
      "/cs61b/collections": [
        {
          "source": "/cs61b/abstract-data-types/collections/arrays",
          "target": "/cs61b/collections",
          "text": "Collections"
        }
      ],
      "/cs61b/misc-topics/exceptions": [
        {
          "source": "/cs61b/",
          "target": "/cs61b/misc-topics/exceptions",
          "text": "Exceptions"
        }
      ],
      "/cs61b/misc-topics/modular-arithmetic": [
        {
          "source": "/cs61b/oop/objects",
          "target": "/cs61b/misc-topics/modular-arithmetic",
          "text": "Modular Arithmetic and Bit Manipulation"
        }
      ],
      "/cs61b/oop/dynamic-method-selection": [
        {
          "source": "/cs61b/",
          "target": "/cs61b/oop/dynamic-method-selection",
          "text": "Dynamic Method Selection"
        }
      ],
      "/cs61b/oop/generics": [
        {
          "source": "/cs61b/abstract-data-types/collections/arrays",
          "target": "/cs61b/oop/generics",
          "text": "Generic Types"
        }
      ],
      "/cs61b/oop/objects": [
        {
          "source": "/cs61b/abstract-data-types/collections/arrays",
          "target": "/cs61b/oop/objects",
          "text": "Java Objects"
        },
        {
          "source": "/cs61b/misc-topics/modular-arithmetic",
          "target": "/cs61b/oop/objects",
          "text": "Java Objects"
        }
      ],
      "/cs70/": [
        {
          "source": "/",
          "target": "/cs70/",
          "text": "CS 70: Discrete Math"
        }
      ],
      "/cs70/discrete-math/polynomials": [
        {
          "source": "/cs70/discrete-math/modular-arithmetic",
          "target": "/cs70/discrete-math/polynomials",
          "text": "error correction"
        },
        {
          "source": "/cs70/discrete-math/rsa-cryptography",
          "target": "/cs70/discrete-math/polynomials",
          "text": "soon"
        }
      ],
      "/cs70/discrete-math/rsa-cryptography": [
        {
          "source": "/cs70/discrete-math/modular-arithmetic",
          "target": "/cs70/discrete-math/rsa-cryptography",
          "text": "cryptography"
        },
        {
          "source": "/cs70/discrete-math/modular-arithmetic",
          "target": "/cs70/discrete-math/rsa-cryptography",
          "text": "RSA Cryptography"
        }
      ],
      "/cs70/latex-reference": [
        {
          "source": "/cs70/",
          "target": "/cs70/latex-reference",
          "text": "LaTeX Reference"
        }
      ],
      "/cs70/probability/concentration-inequalities": [
        {
          "source": "/cs70/probability/probability-overview",
          "target": "/cs70/probability/concentration-inequalities",
          "text": "Concentration inequalities"
        }
      ],
      "/cs70/probability/continuous-probability": [
        {
          "source": "/cs70/probability/probability-overview",
          "target": "/cs70/probability/continuous-probability",
          "text": "Continuous probability distributions"
        }
      ],
      "/cs70/probability/counting": [
        {
          "source": "/cs70/probability/probability-overview",
          "target": "/cs70/probability/counting",
          "text": "Counting"
        }
      ],
      "/cs70/probability/discrete-probability": [
        {
          "source": "/cs70/probability/probability-overview",
          "target": "/cs70/probability/discrete-probability",
          "text": "Discrete probability distributions"
        }
      ],
      "/cs70/probability/expectation-and-variance": [
        {
          "source": "/cs70/probability/probability-overview",
          "target": "/cs70/probability/expectation-and-variance",
          "text": "Expectation and variance"
        }
      ],
      "/cs70/probability/markov-chains": [
        {
          "source": "/cs70/probability/probability-overview",
          "target": "/cs70/probability/markov-chains",
          "text": "Markov chains"
        }
      ],
      "/data102/": [
        {
          "source": "/",
          "target": "/data102/",
          "text": "Data 102: Data, Inference, Decisions"
        }
      ],
      "/data102/concentration%20inequalities": [
        {
          "source": "/cs70/probability/concentration-inequalities",
          "target": "/data102/concentration%20inequalities",
          "text": "Data 102 notes"
        }
      ],
      "/depth-first-search-dfs": [
        {
          "source": "/cs61b/algorithms/searching/breadth-first-search-bfs",
          "target": "/depth-first-search-dfs",
          "text": "Depth First Search (DFS)"
        }
      ],
      "/dijkstras-algorithm": [
        {
          "source": "/cs61b/algorithms/shortest-paths/a-search",
          "target": "/dijkstras-algorithm",
          "text": "Dijkstra's Algorithm"
        }
      ],
      "/dynamic-method-selection": [
        {
          "source": "/cs61b/oop/generics",
          "target": "/dynamic-method-selection",
          "text": "Dynamic Method Selection"
        },
        {
          "source": "/cs61b/oop/inheritance",
          "target": "/dynamic-method-selection",
          "text": "Dynamic Method Selection"
        }
      ],
      "/generics": [
        {
          "source": "/cs61b/oop/inheritance",
          "target": "/generics",
          "text": "Generic Types"
        }
      ],
      "/hypothesis-testing": [
        {
          "source": "/data102/decision-theory",
          "target": "/hypothesis-testing",
          "text": "hypothesis testing"
        }
      ],
      "/inheritance": [
        {
          "source": "/cs61b/oop/dynamic-method-selection",
          "target": "/inheritance",
          "text": "inheritance"
        },
        {
          "source": "/cs61b/oop/dynamic-method-selection",
          "target": "/inheritance",
          "text": "Interfaces"
        },
        {
          "source": "/cs61b/oop/generics",
          "target": "/inheritance",
          "text": "inheritance rules"
        }
      ],
      "/intradomain-routing": [
        {
          "source": "/cs168/interdomain-routing-bgp",
          "target": "/intradomain-routing",
          "text": "intradomain routing"
        },
        {
          "source": "/cs168/interdomain-routing-bgp",
          "target": "/intradomain-routing",
          "text": "intradomain routing"
        }
      ],
      "/io": [
        {
          "source": "/cs186/",
          "target": "/io",
          "text": "What is an I/O and why should I care?"
        }
      ],
      "/linked-lists": [
        {
          "source": "/cs61b/abstract-data-types/collections/",
          "target": "/linked-lists",
          "text": "Linked Lists"
        }
      ],
      "/modular-arithmetic": [
        {
          "source": "/cs70/discrete-math/overview",
          "target": "/modular-arithmetic",
          "text": "Modular arithmetic"
        }
      ],
      "/objects": [
        {
          "source": "/cs61b/oop/inheritance",
          "target": "/objects",
          "text": "References, Objects, and Types in Java"
        }
      ],
      "/polynomials": [
        {
          "source": "/cs70/discrete-math/overview",
          "target": "/polynomials",
          "text": "Polynomials"
        }
      ],
      "/proofs": [
        {
          "source": "/cs70/discrete-math/overview",
          "target": "/proofs",
          "text": "Proofs"
        }
      ],
      "/propositional-logic": [
        {
          "source": "/cs70/discrete-math/overview",
          "target": "/propositional-logic",
          "text": "Propositional logic"
        }
      ],
      "/reliability": [
        {
          "source": "/cs168/TCP",
          "target": "/reliability",
          "text": "reliability"
        }
      ],
      "/resource-sharing-packet-and-circuit-switching": [
        {
          "source": "/cs168/congestion-control",
          "target": "/resource-sharing-packet-and-circuit-switching",
          "text": "resource sharing (packet and circuit switching)"
        }
      ],
      "/rsa-cryptography": [
        {
          "source": "/cs70/discrete-math/overview",
          "target": "/rsa-cryptography",
          "text": "RSA Cryptography"
        }
      ],
      "/stable-matching": [
        {
          "source": "/cs70/discrete-math/overview",
          "target": "/stable-matching",
          "text": "Stable Matching"
        }
      ],
      "/tries": [
        {
          "source": "/cs61b/abstract-data-types/binary-trees/",
          "target": "/tries",
          "text": "Tries"
        }
      ]
    }
  },
  "links": [
    {
      "source": "/",
      "target": "/cs61b/",
      "text": "CS 61B: Data Structures and Algorithms"
    },
    {
      "source": "/",
      "target": "/cs70/",
      "text": "CS 70: Discrete Math"
    },
    {
      "source": "/",
      "target": "/cs186/",
      "text": "CS 186: Intro to Databases"
    },
    {
      "source": "/",
      "target": "/cs162/",
      "text": "CS 162: Operating Systems"
    },
    {
      "source": "/",
      "target": "/cs168/",
      "text": "CS 168: Intro to the Internet"
    },
    {
      "source": "/",
      "target": "/cs61a/",
      "text": "CS 61A: Structure and Interpretation of Computer Programs"
    },
    {
      "source": "/",
      "target": "/data102/",
      "text": "Data 102: Data, Inference, Decisions"
    },
    {
      "source": "/",
      "target": "/contributing",
      "text": "contributing"
    },
    {
      "source": "/",
      "target": "/contributing",
      "text": "contribution guide"
    },
    {
      "source": "/cs162/",
      "target": "/Chapter-1-OS-Basics",
      "text": "OS Basics"
    },
    {
      "source": "/cs162/",
      "target": "/Chapter-2-Processes",
      "text": "Processes"
    },
    {
      "source": "/cs162/",
      "target": "/Chapter-3-Threads",
      "text": "Threads"
    },
    {
      "source": "/cs162/",
      "target": "/Chapter-4-I-O",
      "text": "IO"
    },
    {
      "source": "/cs162/",
      "target": "/Chapter-5-Synchronization",
      "text": "Synchronization"
    },
    {
      "source": "/cs162/",
      "target": "/Chapter-6-Scheduling",
      "text": "Scheduling"
    },
    {
      "source": "/cs162/",
      "target": "/Chapter-7-Address-Translation",
      "text": "Address Translation"
    },
    {
      "source": "/cs162/",
      "target": "/Chapter-8-Caching",
      "text": "Caching"
    },
    {
      "source": "/cs162/",
      "target": "/Chapter-9-File-Systems",
      "text": "File Systems"
    },
    {
      "source": "/cs162/",
      "target": "/Appendix-A-GDB-foobars",
      "text": "GDB Reference"
    },
    {
      "source": "/cs162/",
      "target": "/contributing",
      "text": "contributing guide"
    },
    {
      "source": "/cs162/",
      "target": "/cs162/Chapter-8-Caching",
      "text": "Caching"
    },
    {
      "source": "/cs162/",
      "target": "/cs162/Chapter-5-Synchronization",
      "text": "Synchronization"
    },
    {
      "source": "/cs168/TCP",
      "target": "/reliability",
      "text": "reliability"
    },
    {
      "source": "/cs168/TCP",
      "target": "/congestion-control",
      "text": "congestion control"
    },
    {
      "source": "/cs168/",
      "target": "/Intro-to-the-Internet",
      "text": "Intro to the Internet"
    },
    {
      "source": "/cs168/",
      "target": "/CLI",
      "text": "CLI Tools"
    },
    {
      "source": "/cs168/",
      "target": "/Intradomain-Routing",
      "text": "Intradomain Routing"
    },
    {
      "source": "/cs168/",
      "target": "/Measuring-Link-Performance",
      "text": "Measuring Link Performance"
    },
    {
      "source": "/cs168/",
      "target": "/Resource-Sharing-Packet-and-Circuit-Switching",
      "text": "Resource Sharing (Packet and Circuit Switching)"
    },
    {
      "source": "/cs168/",
      "target": "/Internet-Organization-and-Layers",
      "text": "Internet Organization and Layers"
    },
    {
      "source": "/cs168/",
      "target": "/Sockets-and-Ports",
      "text": "Sockets and Ports"
    },
    {
      "source": "/cs168/",
      "target": "/Addressing-IP",
      "text": "Addressing (IP)"
    },
    {
      "source": "/cs168/",
      "target": "/Interdomain-Routing-BGP",
      "text": "Interdomain Routing (BGP)"
    },
    {
      "source": "/cs168/",
      "target": "/TCP",
      "text": "TCP"
    },
    {
      "source": "/cs168/",
      "target": "/Reliability",
      "text": "Reliability"
    },
    {
      "source": "/cs168/",
      "target": "/Congestion-Control",
      "text": "Congestion Control"
    },
    {
      "source": "/cs168/",
      "target": "/DNS",
      "text": "DNS"
    },
    {
      "source": "/cs168/",
      "target": "/Web",
      "text": "Web"
    },
    {
      "source": "/cs168/",
      "target": "/Ethernet",
      "text": "Ethernet"
    },
    {
      "source": "/cs168/",
      "target": "/End-to-End-Operation",
      "text": "End to End Operation"
    },
    {
      "source": "/cs168/",
      "target": "/Final-Review",
      "text": "Final Review"
    },
    {
      "source": "/cs168/",
      "target": "/contributing",
      "text": "contributing guide"
    },
    {
      "source": "/cs168/congestion-control",
      "target": "/resource-sharing-packet-and-circuit-switching",
      "text": "resource sharing (packet and circuit switching)"
    },
    {
      "source": "/cs168/ethernet",
      "target": "/",
      "text": "#Pure ALOHA random access"
    },
    {
      "source": "/cs168/final-review",
      "target": "/",
      "text": "#SDN"
    },
    {
      "source": "/cs168/interdomain-routing-bgp",
      "target": "/intradomain-routing",
      "text": "intradomain routing"
    },
    {
      "source": "/cs168/interdomain-routing-bgp",
      "target": "/addressing-ip",
      "text": "addressing (ip)"
    },
    {
      "source": "/cs168/interdomain-routing-bgp",
      "target": "/intradomain-routing",
      "text": "intradomain routing"
    },
    {
      "source": "/cs186/00-SQL-Basics",
      "target": "/",
      "text": "table creation"
    },
    {
      "source": "/cs186/00-SQL-Basics",
      "target": "/01-Disks-Buffers-Files",
      "text": "next section"
    },
    {
      "source": "/cs186/01-Disks-Buffers-Files",
      "target": "/cs186/00%20SQL%20Basics",
      "text": "SQL"
    },
    {
      "source": "/cs186/01-Disks-Buffers-Files",
      "target": "/cs186/io",
      "text": "What is an I/O and why should I care?"
    },
    {
      "source": "/cs186/01-Disks-Buffers-Files",
      "target": "/cs186/11-Distributed-Transactions",
      "text": "Distributed Transactions"
    },
    {
      "source": "/cs186/01-Disks-Buffers-Files",
      "target": "/",
      "text": "Practice Problems section"
    },
    {
      "source": "/cs186/01-Disks-Buffers-Files",
      "target": "/cs186/02-B+-Trees",
      "text": "B+ Trees"
    },
    {
      "source": "/cs186/07-Query-Optimization",
      "target": "/",
      "text": "practice"
    },
    {
      "source": "/cs186/",
      "target": "/cs186/00-SQL-Basics",
      "text": "SQL syntax"
    },
    {
      "source": "/cs186/",
      "target": "/cs186/04-Sorting-and-Hashing",
      "text": "How to improve popular sorting and hashing algorithms to work well with limited memory"
    },
    {
      "source": "/cs186/",
      "target": "/cs186/02-B+-Trees",
      "text": "B+ trees"
    },
    {
      "source": "/cs186/",
      "target": "/cs186/05-Iterators-and-Joins",
      "text": "Join algorithms"
    },
    {
      "source": "/cs186/",
      "target": "/cs186/07-Query-Optimization",
      "text": "Query optimization"
    },
    {
      "source": "/cs186/",
      "target": "/cs186/09-Parallel-Query-Processing",
      "text": "Parallel query processing"
    },
    {
      "source": "/cs186/",
      "target": "/cs186/10-Recovery",
      "text": "Crash Recovery (AERIES)"
    },
    {
      "source": "/cs186/",
      "target": "/cs186/08-Transactions",
      "text": "Database transactions and Concurrency"
    },
    {
      "source": "/cs186/",
      "target": "/cs186/12-ER-Diagrams",
      "text": "Entity-Relationship Diagrams"
    },
    {
      "source": "/cs186/",
      "target": "/io",
      "text": "What is an I/O and why should I care?"
    },
    {
      "source": "/cs186/",
      "target": "/cs61b",
      "text": "CS61B"
    },
    {
      "source": "/cs186/",
      "target": "/cs61b",
      "text": "CS61B notes"
    },
    {
      "source": "/cs186/",
      "target": "/cs186/01-Disks-Buffers-Files",
      "text": "Disks, Buffers, Files"
    },
    {
      "source": "/cs186/",
      "target": "/contributing",
      "text": "contributing guide"
    },
    {
      "source": "/cs186/io",
      "target": "/cs186/07-Query-Optimization",
      "text": "query optimization"
    },
    {
      "source": "/cs61a/",
      "target": "/cs61a/resources",
      "text": "here"
    },
    {
      "source": "/cs61a/",
      "target": "/cs61a/midterm-tips",
      "text": "here"
    },
    {
      "source": "/cs61b/",
      "target": "/cs61b/oop/dynamic-method-selection",
      "text": "Dynamic Method Selection"
    },
    {
      "source": "/cs61b/",
      "target": "/cs61b/asymptotics/asymptotics-practice",
      "text": "Asymptotics Practice"
    },
    {
      "source": "/cs61b/",
      "target": "/contributing",
      "text": "contributing guide"
    },
    {
      "source": "/cs61b/",
      "target": "/cs61b/abstract-data-types/union-find-disjoint-sets",
      "text": "Union Find (Disjoint Sets)"
    },
    {
      "source": "/cs61b/",
      "target": "/cs61b/abstract-data-types/collections/stacks-and-queues",
      "text": "Stacks and Queues"
    },
    {
      "source": "/cs61b/",
      "target": "/cs61b/abstract-data-types/collections/linked-lists",
      "text": "Linked Lists"
    },
    {
      "source": "/cs61b/",
      "target": "/cs61b/abstract-data-types/collections/sets",
      "text": "Sets"
    },
    {
      "source": "/cs61b/",
      "target": "/algorithms/sorting",
      "text": "Sorting"
    },
    {
      "source": "/cs61b/",
      "target": "/cs61b/algorithms/searching",
      "text": "Searching"
    },
    {
      "source": "/cs61b/",
      "target": "/cs61b/algorithms/searching/binary-search",
      "text": "Binary Search"
    },
    {
      "source": "/cs61b/",
      "target": "/cs61b/algorithms/shortest-paths/",
      "text": "Shortest Paths"
    },
    {
      "source": "/cs61b/",
      "target": "/cs61b/misc-topics/exceptions",
      "text": "Exceptions"
    },
    {
      "source": "/cs61b/abstract-data-types/binary-trees/",
      "target": "/../../algorithms/searching/binary-search",
      "text": "Binary Search"
    },
    {
      "source": "/cs61b/abstract-data-types/binary-trees/",
      "target": "/balanced-search-structures",
      "text": "Balanced BSTs"
    },
    {
      "source": "/cs61b/abstract-data-types/binary-trees/",
      "target": "/../graphs",
      "text": "Graphs"
    },
    {
      "source": "/cs61b/abstract-data-types/binary-trees/",
      "target": "/tries",
      "text": "Tries"
    },
    {
      "source": "/cs61b/abstract-data-types/binary-trees/",
      "target": "/../hashing",
      "text": "Hash Tables"
    },
    {
      "source": "/cs61b/abstract-data-types/binary-trees/",
      "target": "/../../algorithms/searching/depth-first-search-dfs",
      "text": "Depth First Search"
    },
    {
      "source": "/cs61b/abstract-data-types/binary-trees/",
      "target": "/../../algorithms/searching/breadth-first-search-bfs",
      "text": "Breadth First Search"
    },
    {
      "source": "/cs61b/abstract-data-types/binary-trees/balanced-search-structures",
      "target": "/cs61b/binary-trees",
      "text": "Binary Trees"
    },
    {
      "source": "/cs61b/abstract-data-types/binary-trees/tries",
      "target": "/cs61b/abstract-data-types/hashing",
      "text": "Hashing and Hash Tables"
    },
    {
      "source": "/cs61b/abstract-data-types/binary-trees/tries",
      "target": "/cs61b/abstract-data-types/collections/sets",
      "text": "Sets"
    },
    {
      "source": "/cs61b/abstract-data-types/collections/",
      "target": "/linked-lists",
      "text": "Linked Lists"
    },
    {
      "source": "/cs61b/abstract-data-types/collections/",
      "target": "/cs61b/abstract-data-types/collections/sets",
      "text": "Sets"
    },
    {
      "source": "/cs61b/abstract-data-types/collections/",
      "target": "/cs61b/abstract-data-types/hashing",
      "text": "Hashing and Hash Tables"
    },
    {
      "source": "/cs61b/abstract-data-types/collections/",
      "target": "/cs61b/abstract-data-types/collections/stacks-and-queues",
      "text": "Stacks and Queues"
    },
    {
      "source": "/cs61b/abstract-data-types/collections/arrays",
      "target": "/cs61b/oop/objects",
      "text": "Java Objects"
    },
    {
      "source": "/cs61b/abstract-data-types/collections/arrays",
      "target": "/cs61b/oop/generics",
      "text": "Generic Types"
    },
    {
      "source": "/cs61b/abstract-data-types/collections/arrays",
      "target": "/cs61b/collections",
      "text": "Collections"
    },
    {
      "source": "/cs61b/abstract-data-types/collections/linked-lists",
      "target": "/arrays",
      "text": "Arrays"
    },
    {
      "source": "/cs61b/abstract-data-types/collections/sets",
      "target": "/contributing",
      "text": "help make it better!"
    },
    {
      "source": "/cs61b/abstract-data-types/collections/sets",
      "target": "/../../asymptotics/amortization",
      "text": "resized"
    },
    {
      "source": "/cs61b/abstract-data-types/collections/stacks-and-queues",
      "target": "/cs61b/algorithms/shortest-paths/dijkstras-algorithm",
      "text": "finding shortest paths using Dijkstra's Algorithm"
    },
    {
      "source": "/cs61b/abstract-data-types/graphs",
      "target": "/cs61b/algorithms/searching/depth-first-search-dfs",
      "text": "Depth First Search (DFS)"
    },
    {
      "source": "/cs61b/abstract-data-types/graphs",
      "target": "/cs61b/algorithms/searching/breadth-first-search-bfs",
      "text": "Breadth First Search (BFS)"
    },
    {
      "source": "/cs61b/abstract-data-types/graphs",
      "target": "/cs61b/algorithms/minimum-spanning-trees/",
      "text": "Minimum Spanning Trees"
    },
    {
      "source": "/cs61b/abstract-data-types/graphs",
      "target": "/cs61b/algorithms/shortest-paths/",
      "text": "Shortest Paths"
    },
    {
      "source": "/cs61b/abstract-data-types/graphs",
      "target": "/cs61b/algorithms/shortest-paths/dijkstras-algorithm",
      "text": "Dijkstra's Algorithm"
    },
    {
      "source": "/cs61b/abstract-data-types/graphs",
      "target": "/cs61b/algorithms/shortest-paths/a-search",
      "text": "A* Search"
    },
    {
      "source": "/cs61b/abstract-data-types/graphs",
      "target": "/cs61b/algorithms/minimum-spanning-trees/prims-algorithm",
      "text": "Prim's Algorithm"
    },
    {
      "source": "/cs61b/abstract-data-types/graphs",
      "target": "/cs61b/algorithms/minimum-spanning-trees/kruskals-algorithm",
      "text": "Kruskal's Algorithm"
    },
    {
      "source": "/cs61b/abstract-data-types/hashing",
      "target": "/cs61b/asymptotics/amortization",
      "text": "Amortization"
    },
    {
      "source": "/cs61b/abstract-data-types/union-find-disjoint-sets",
      "target": "/cs61b/algorithms/minimum-spanning-trees/kruskals-algorithm",
      "text": "Kruskal's Algorithm"
    },
    {
      "source": "/cs61b/algorithms/minimum-spanning-trees/kruskals-algorithm",
      "target": "/./",
      "text": "Minimum Spanning Trees"
    },
    {
      "source": "/cs61b/algorithms/minimum-spanning-trees/kruskals-algorithm",
      "target": "/../../abstract-data-types/union-find-disjoint-sets",
      "text": "Union Find (Disjoint Sets)"
    },
    {
      "source": "/cs61b/algorithms/minimum-spanning-trees/kruskals-algorithm",
      "target": "/../../abstract-data-types/union-find-disjoint-sets",
      "text": "Union Find (Disjoint Sets)"
    },
    {
      "source": "/cs61b/algorithms/minimum-spanning-trees/kruskals-algorithm",
      "target": "/../../abstract-data-types/collections/stacks-and-queues",
      "text": "PriorityQueue"
    },
    {
      "source": "/cs61b/algorithms/minimum-spanning-trees/prims-algorithm",
      "target": "/./",
      "text": "Minimum Spanning Trees"
    },
    {
      "source": "/cs61b/algorithms/minimum-spanning-trees/prims-algorithm",
      "target": "/../../abstract-data-types/collections/stacks-and-queues",
      "text": "PriorityQueue"
    },
    {
      "source": "/cs61b/algorithms/minimum-spanning-trees/prims-algorithm",
      "target": "/../shortest-paths/dijkstras-algorithm",
      "text": "Dijkstra's"
    },
    {
      "source": "/cs61b/algorithms/searching/binary-search",
      "target": "/../../abstract-data-types/binary-trees/",
      "text": "binary trees"
    },
    {
      "source": "/cs61b/algorithms/searching/breadth-first-search-bfs",
      "target": "/depth-first-search-dfs",
      "text": "Depth First Search (DFS)"
    },
    {
      "source": "/cs61b/algorithms/searching/breadth-first-search-bfs",
      "target": "/../shortest-paths/dijkstras-algorithm",
      "text": "Dijkstra's Algorithm"
    },
    {
      "source": "/cs61b/algorithms/shortest-paths/a-search",
      "target": "/dijkstras-algorithm",
      "text": "Dijkstra's Algorithm"
    },
    {
      "source": "/cs61b/algorithms/shortest-paths/dijkstras-algorithm",
      "target": "/../../abstract-data-types/graphs",
      "text": "Graphs"
    },
    {
      "source": "/cs61b/algorithms/shortest-paths/dijkstras-algorithm",
      "target": "/../../abstract-data-types/collections/stacks-and-queues",
      "text": "Stacks and Queues"
    },
    {
      "source": "/cs61b/algorithms/shortest-paths/dijkstras-algorithm",
      "target": "/./",
      "text": "Shortest Paths"
    },
    {
      "source": "/cs61b/asymptotics/amortization",
      "target": "/asymptotics",
      "text": "Asymptotic Analysis Basics"
    },
    {
      "source": "/cs61b/asymptotics/asymptotics-practice",
      "target": "/asymptotics",
      "text": "Asymptotic Analysis Basics"
    },
    {
      "source": "/cs61b/asymptotics/asymptotics",
      "target": "/asymptotics-practice",
      "text": "try some problems!"
    },
    {
      "source": "/cs61b/asymptotics/asymptotics",
      "target": "/asymptotics",
      "text": "Simplify"
    },
    {
      "source": "/cs61b/misc-topics/modular-arithmetic",
      "target": "/cs61b/oop/objects",
      "text": "Java Objects"
    },
    {
      "source": "/cs61b/oop/dynamic-method-selection",
      "target": "/inheritance",
      "text": "inheritance"
    },
    {
      "source": "/cs61b/oop/dynamic-method-selection",
      "target": "/access-control",
      "text": "access control"
    },
    {
      "source": "/cs61b/oop/dynamic-method-selection",
      "target": "/inheritance",
      "text": "Interfaces"
    },
    {
      "source": "/cs61b/oop/dynamic-method-selection",
      "target": "/../abstract-data-types/collections/",
      "text": "Collections"
    },
    {
      "source": "/cs61b/oop/generics",
      "target": "/dynamic-method-selection",
      "text": "Dynamic Method Selection"
    },
    {
      "source": "/cs61b/oop/generics",
      "target": "/inheritance",
      "text": "inheritance rules"
    },
    {
      "source": "/cs61b/oop/inheritance",
      "target": "/access-control",
      "text": "Access Control"
    },
    {
      "source": "/cs61b/oop/inheritance",
      "target": "/objects",
      "text": "References, Objects, and Types in Java"
    },
    {
      "source": "/cs61b/oop/inheritance",
      "target": "/generics",
      "text": "Generic Types"
    },
    {
      "source": "/cs61b/oop/inheritance",
      "target": "/dynamic-method-selection",
      "text": "Dynamic Method Selection"
    },
    {
      "source": "/cs61b/oop/objects",
      "target": "/cs61b/misc-topics/modular-arithmetic",
      "text": "Modular Arithmetic and Bit Manipulation"
    },
    {
      "source": "/cs61b/oop/objects",
      "target": "/../abstract-data-types/collections/",
      "text": "collections"
    },
    {
      "source": "/cs70/",
      "target": "/contributing",
      "text": "contributing guide"
    },
    {
      "source": "/cs70/",
      "target": "/cs70/latex-reference",
      "text": "LaTeX Reference"
    },
    {
      "source": "/cs70/discrete-math/graphs",
      "target": "/cs61b/abstract-data-types/graphs",
      "text": "61B version"
    },
    {
      "source": "/cs70/discrete-math/modular-arithmetic",
      "target": "/cs70/discrete-math/rsa-cryptography",
      "text": "cryptography"
    },
    {
      "source": "/cs70/discrete-math/modular-arithmetic",
      "target": "/cs70/discrete-math/polynomials",
      "text": "error correction"
    },
    {
      "source": "/cs70/discrete-math/modular-arithmetic",
      "target": "/cs70/discrete-math/rsa-cryptography",
      "text": "RSA Cryptography"
    },
    {
      "source": "/cs70/discrete-math/overview",
      "target": "/propositional-logic",
      "text": "Propositional logic"
    },
    {
      "source": "/cs70/discrete-math/overview",
      "target": "/proofs",
      "text": "Proofs"
    },
    {
      "source": "/cs70/discrete-math/overview",
      "target": "/stable-matching",
      "text": "Stable Matching"
    },
    {
      "source": "/cs70/discrete-math/overview",
      "target": "/classes/cs70/discrete-math/graphs",
      "text": "Graph theory"
    },
    {
      "source": "/cs70/discrete-math/overview",
      "target": "/modular-arithmetic",
      "text": "Modular arithmetic"
    },
    {
      "source": "/cs70/discrete-math/overview",
      "target": "/rsa-cryptography",
      "text": "RSA Cryptography"
    },
    {
      "source": "/cs70/discrete-math/overview",
      "target": "/polynomials",
      "text": "Polynomials"
    },
    {
      "source": "/cs70/discrete-math/rsa-cryptography",
      "target": "/cs70/discrete-math/polynomials",
      "text": "soon"
    },
    {
      "source": "/cs70/probability/concentration-inequalities",
      "target": "/data102/concentration%20inequalities",
      "text": "Data 102 notes"
    },
    {
      "source": "/cs70/probability/probability-overview",
      "target": "/cs70/probability/counting",
      "text": "Counting"
    },
    {
      "source": "/cs70/probability/probability-overview",
      "target": "/cs70/probability/discrete-probability",
      "text": "Discrete probability distributions"
    },
    {
      "source": "/cs70/probability/probability-overview",
      "target": "/cs70/probability/continuous-probability",
      "text": "Continuous probability distributions"
    },
    {
      "source": "/cs70/probability/probability-overview",
      "target": "/cs70/probability/markov-chains",
      "text": "Markov chains"
    },
    {
      "source": "/cs70/probability/probability-overview",
      "target": "/cs70/probability/expectation-and-variance",
      "text": "Expectation and variance"
    },
    {
      "source": "/cs70/probability/probability-overview",
      "target": "/cs70/probability/concentration-inequalities",
      "text": "Concentration inequalities"
    },
    {
      "source": "/data102/",
      "target": "/Binary-Decision-Making",
      "text": "Binary Decision Making"
    },
    {
      "source": "/data102/",
      "target": "/Hypothesis-Testing",
      "text": "Hypothesis Testing"
    },
    {
      "source": "/data102/",
      "target": "/Decision-Theory",
      "text": "Decision Theory"
    },
    {
      "source": "/data102/",
      "target": "/Parameter-Estimation",
      "text": "Parameter Estimation"
    },
    {
      "source": "/data102/",
      "target": "/Sampling",
      "text": "Sampling"
    },
    {
      "source": "/data102/",
      "target": "/Regression-and-GLMs",
      "text": "Regression and GLMs"
    },
    {
      "source": "/data102/",
      "target": "/Nonparametric-Methods",
      "text": "Nonparametric Methods"
    },
    {
      "source": "/data102/",
      "target": "/Interpretability",
      "text": "Interpretability"
    },
    {
      "source": "/data102/",
      "target": "/Causality",
      "text": "Causality"
    },
    {
      "source": "/data102/",
      "target": "/Concentration-Inequalities",
      "text": "Concentration Inequalities"
    },
    {
      "source": "/data102/",
      "target": "/Bandits",
      "text": "Bandits"
    },
    {
      "source": "/data102/",
      "target": "/Markov-Decision-Processes",
      "text": "Markov Decision Processes"
    },
    {
      "source": "/data102/",
      "target": "/Reinforcement-Learning",
      "text": "Reinforcement Learning"
    },
    {
      "source": "/data102/",
      "target": "/contributing",
      "text": "contributing guide"
    },
    {
      "source": "/data102/causality",
      "target": "/04-Bayes-Nets",
      "text": "04 Bayes Nets"
    },
    {
      "source": "/data102/decision-theory",
      "target": "/binary-decision-making",
      "text": "binary decision making"
    },
    {
      "source": "/data102/decision-theory",
      "target": "/hypothesis-testing",
      "text": "hypothesis testing"
    },
    {
      "source": "/data102/hypothesis-testing",
      "target": "/binary-decision-making",
      "text": "binary decision making"
    },
    {
      "source": "/data102/regression-and-glms",
      "target": "/",
      "text": "#Model Checking"
    },
    {
      "source": "/data102/regression-and-glms",
      "target": "/",
      "text": "#Credible Intervals"
    }
  ]
}